vimwiki_to_org/__init__.py
vimwiki_to_org/__main__.py
vimwiki_to_org/src/__init__.py
vimwiki_to_org/src/app.py
vimwiki_to_org/src/converters/__init__.py
vimwiki_to_org/src/converters/vimwiki_to_org.py
vimwiki_to_org/src/converters/helpers/__init__.py
vimwiki_to_org/src/converters/helpers/header_helper.py
vimwiki_to_org/src/converters/helpers/link_helper.py
vimwiki_to_org/src/converters/helpers/org_markdown.py
vimwiki_to_org/src/converters/helpers/prevention_tag.py
vimwiki_to_org/src/converters/helpers/wiki_regex.py
vimwiki_to_org/src/helpers/__init__.py
vimwiki_to_org/src/helpers/progress_bar.py
vimwiki_to_org/tests/__init__.py
vimwiki_to_org/tests/conftest.py
vimwiki_to_org/tests/helpers/__init__.py
vimwiki_to_org/tests/helpers/conversion_checker.py
vimwiki_to_org/tests/helpers/markdown_classifier.py
vimwiki_to_org/tests/helpers/prevention_tag.py
vimwiki_to_org/tests/helpers/text_checks.py
vimwiki_to_org/tests/helpers/text_conversion.py
vimwiki_to_org/tests/helpers/text_formatter.py
vimwiki_to_org/tests/unit/__init__.py
vimwiki_to_org/tests/unit/basic_markdown_conversion_test.py
vimwiki_to_org/tests/unit/markdown_classifiction_test.py
vimwiki_to_org/tests/unit/overwrite_protection_test.py
vimwiki_to_org-1.2.0.dist-info/LICENSE
vimwiki_to_org-1.2.0.dist-info/METADATA
vimwiki_to_org-1.2.0.dist-info/WHEEL
vimwiki_to_org-1.2.0.dist-info/entry_points.txt
vimwiki_to_org-1.2.0.dist-info/top_level.txt
vimwiki_to_org-1.2.0.dist-info/RECORD
