Metadata-Version: 2.1
Name: vimwiki-to-org
Version: 1.2.0
Summary: Converts vimwiki files to org mode
Home-page: https://github.com/CryptoRodeo/VimWikiToOrg
Author: Bryan Ramos
Author-email: Bryan Ramos <bryan.ramos@hey.com>
License: GPLv3
Project-URL: Homepage, https://github.com/CryptoRodeo/VimWikiToOrg
Project-URL: Bug Tracker, https://github.com/CryptoRodeo/VimWikiToOrg/issues
Keywords: vimwiki orgmode convert
Classifier: Programming Language :: Python :: 3
Classifier: License :: OSI Approved :: GNU General Public License v3 (GPLv3)
Classifier: Operating System :: OS Independent
Requires-Python: >=3.10
License-File: LICENSE
